patchmatch/Makefile
patchmatch/__init__.py
patchmatch/patch_match.py
patchmatch/travis.sh
patchmatch/csrc/inpaint.cpp
patchmatch/csrc/inpaint.h
patchmatch/csrc/masked_image.cpp
patchmatch/csrc/masked_image.h
patchmatch/csrc/nnf.cpp
patchmatch/csrc/nnf.h
patchmatch/csrc/pyinterface.cpp
patchmatch/csrc/pyinterface.h
PyPatchMatch-1.0.2.dist-info/LICENSE
PyPatchMatch-1.0.2.dist-info/METADATA
PyPatchMatch-1.0.2.dist-info/WHEEL
PyPatchMatch-1.0.2.dist-info/top_level.txt
PyPatchMatch-1.0.2.dist-info/RECORD
