Metadata-Version: 2.1
Name: PyPatchMatch
Version: 1.0.2
Summary: This library implements the PatchMatch based inpainting algorithm.
Author-email: The InvokeAI Project <lincoln.stein@gmail.com>, Kyle Schouviller <kyle0654@hotmail.com>, Matthias Wild <mauwii@outlook.de>, Younesse ANDAM <younesse.andam@gmail.com>
License: MIT License
Project-URL: Source Code, https://github.com/mauwii/PyPatchMatch
Requires-Python: <3.13,>=3.9
License-File: LICENSE
Requires-Dist: numpy
Requires-Dist: pillow
Requires-Dist: tqdm
Provides-Extra: dev
Requires-Dist: black; extra == "dev"
Requires-Dist: flake8; extra == "dev"
Requires-Dist: flake8-black; extra == "dev"
Requires-Dist: isort; extra == "dev"
Requires-Dist: pre-commit; extra == "dev"
Requires-Dist: pylance; extra == "dev"
Provides-Extra: dist
Requires-Dist: build; extra == "dist"
Requires-Dist: pip-tools; extra == "dist"
Requires-Dist: pipdeptree; extra == "dist"
Requires-Dist: requests; extra == "dist"
Requires-Dist: twine; extra == "dist"
Requires-Dist: delocate; sys_platform == "darwin" and extra == "dist"
Requires-Dist: auditwheel; sys_platform == "linux" and extra == "dist"
Provides-Extra: test
Requires-Dist: pytest; extra == "test"
Requires-Dist: pytest-coverage; extra == "test"
